<?xml version="1.0" encoding="UTF-8"?>
<!--
 -
 -  Developed By:      Intecs  S.P.A.
 -  File Name:         $RCSfile: exportDescriptor.xml,v $
 -  TOOLBOX Version:   $Name:  $
 -  File Revision:     $Revision: 1.2 $
 -  Revision Date:     $Date: 2004/04/28 15:04:15 $
 -
 --><exportDescriptor xmlns="http://pisa.intecs.it/mass/toolbox/exportDescriptor" xmlns:com="http://pisa.intecs.it/mass/toolbox/common" xmlns:dsc="http://pisa.intecs.it/mass/toolbox/serviceDescriptor" xmlns:mtbs="http://pisa.intecs.it/mass/toolbox/xmlScript">
	<service queuing="false" serviceName="S10" serviceSchema="" suspendMode="soft" wsdlTargetNS="" xmlns="http://pisa.intecs.it/mass/toolbox/serviceDescriptor" xmlns:com="http://pisa.intecs.it/mass/toolbox/common" xmlns:mtbs="http://pisa.intecs.it/mass/toolbox/xmlScript">	<schemas/><operations><operation name="RFQ" pollingRate="5s" requestTimeout="30m" type="asynchronous"><wsdlInfo><requestMessage name="sendRFQInputMsg" ns="http://www.esa.int/mass"/><responseMessage name="sendRFQOutputMsg" ns="http://www.esa.int/mass"/><pushMessage name="returnRFQResultInputMsg" ns="http://www.esa.int/mass" soapAction="returnRFQResult"/><pushResponse name="returnRFQResultOutputMsg" ns="http://www.esa.int/mass"/></wsdlInfo><admittedHosts/><script soapAction="sendRFQ"><sequence xmlns="http://pisa.intecs.it/mass/toolbox/xmlScript">	<setVariable name="maxUserQuota">		<literal type="int" value="1000"/>	</setVariable>	<setVariable name="date">		<string>22-2-2003</string>	</setVariable>	<setVariable name="response">		<loadXML>			<string>/home/toolbox/TestEnvironment/Responses/RFQ_response_TS_11_01.xml</string>		</loadXML>	</setVariable>	<setVariable name="checkResponse">		<literal type="boolean" value="true"/>	</setVariable></sequence></script><script><variable name="checkResponse" xmlns="http://pisa.intecs.it/mass/toolbox/xmlScript"/></script><script><sequence xmlns="http://pisa.intecs.it/mass/toolbox/xmlScript">	<log level="INFO">		<variable name="maxUserQuota"/>	</log>	<log level="INFO">		<variable name="date"/>	</log>	<xmlGetResponse>		<variable name="response"/>	</xmlGetResponse></sequence></script></operation></operations></service>
	<schemaDocuments/>
</exportDescriptor>